phantomwire/__init__.py
phantomwire/appsec/__init__.py
phantomwire/appsec/http_headers.py
phantomwire/appsec/jwt_lint.py
phantomwire/appsec/tls_audit.py
phantomwire/cli/__init__.py
phantomwire/cli/main.py
phantomwire/core/config.py
phantomwire/core/models.py
phantomwire/core/pipeline.py
phantomwire/core/registry.py
phantomwire/core/safemode.py
phantomwire/core/utils.py
phantomwire/dns/__init__.py
phantomwire/dns/resolv.py
phantomwire/net/__init__.py
phantomwire/net/pcap.py
phantomwire/reporting/__init__.py
phantomwire/reporting/jsonout.py
phantomwire/reporting/markdown.py
phantomwire/reporting/sarif.py
plugins/example_plugin.py
phantomwire-0.1.1.dist-info/METADATA
phantomwire-0.1.1.dist-info/WHEEL
phantomwire-0.1.1.dist-info/entry_points.txt
phantomwire-0.1.1.dist-info/licenses/LICENSE
phantomwire-0.1.1.dist-info/RECORD
