Metadata-Version: 2.4
Name: phantomwire
Version: 0.1.1
Summary: Defensive-offensive cybersecurity and networking analysis toolkit
Project-URL: Homepage, https://github.com/thesmartshadow/phantomwire
Project-URL: Documentation, https://github.com/thesmartshadow/phantomwire#readme
Project-URL: Bug Tracker, https://github.com/thesmartshadow/phantomwire/issues
Author-email: Phantomwire Maintainers <maintainers@phantomwire.org>
License: MIT
License-File: LICENSE
Classifier: Development Status :: 3 - Alpha
Classifier: Intended Audience :: Information Technology
Classifier: Intended Audience :: Science/Research
Classifier: License :: OSI Approved :: MIT License
Classifier: Natural Language :: English
Classifier: Operating System :: OS Independent
Classifier: Programming Language :: Python :: 3
Classifier: Programming Language :: Python :: 3.10
Classifier: Programming Language :: Python :: 3.11
Classifier: Programming Language :: Python :: 3.12
Classifier: Topic :: Security
Classifier: Topic :: System :: Networking :: Monitoring
Requires-Python: >=3.10
Provides-Extra: crypto
Requires-Dist: cryptography>=43; extra == 'crypto'
Provides-Extra: dev
Requires-Dist: build>=1; extra == 'dev'
Requires-Dist: coverage>=7; extra == 'dev'
Requires-Dist: hypothesis>=6; extra == 'dev'
Requires-Dist: mypy>=1.11; extra == 'dev'
Requires-Dist: pytest-cov>=4; extra == 'dev'
Requires-Dist: pytest>=8; extra == 'dev'
Requires-Dist: ruff>=0.6; extra == 'dev'
Requires-Dist: twine>=5; extra == 'dev'
Provides-Extra: dns
Requires-Dist: dnspython>=2.6; extra == 'dns'
Provides-Extra: pcap
Requires-Dist: dpkt>=1.9.8; extra == 'pcap'
Provides-Extra: web
Requires-Dist: httpx>=0.27; extra == 'web'
